{
  "Enemy Manager": {
    "Average Update GameTick Time": 0.044761675102040765,
    "Min Update Game Tick time": 3.75E-4,
    "Amount of game ticks executed": 4900,
    "metrics": {
      "Enemy Manager - Trigger Enemy Actions": 0.025630996734693556,
      "Enemy Manager - Update Enemies": 0.012518396734693857,
      "Enemy Manager - Move Enemy": 0.003913284376463223,
      "Enemy Manager - Check Spaceship Collision": 0.004325908571428496,
      "Enemy Manager - Update Enemy Effects": 0.0042247746215077426,
      "Enemy Manager - Update GameTick Total": 0.044761675102040765
    },
    "Slow game ticks (x3.5 average)": 146,
    "Max Update GameTick time": 10.357625
  },
  "Background Manager": {
    "Average Update GameTick Time": 0.009626732857142835,
    "Min Update Game Tick time": 9.17E-4,
    "Amount of game ticks executed": 4900,
    "metrics": {
      "Background Manager - Update Objects": 0.007837263224500051,
      "Background Manager - Update GameTick Total": 0.009626732857142835
    },
    "Slow game ticks (x3.5 average)": 50,
    "Max Update GameTick time": 1.747416
  },
  "Animation Manager": {
    "Average Update GameTick Time": 0.004967177142857115,
    "Min Update Game Tick time": 3.33E-4,
    "Amount of game ticks executed": 4900,
    "metrics": {
      "Animation Manager - Remove Invisible Animations": 6.958673469387754E-4,
      "Animation Manager - Recenter Animations": 0.0017873244897959265,
      "Animation Manager - Update GameTick Total": 0.004967177142857115
    },
    "Slow game ticks (x3.5 average)": 65,
    "Max Update GameTick time": 1.264333
  },
  "Player Manager": {
    "Average Update GameTick Time": 0.013509925306122455,
    "Min Update Game Tick time": 7.5E-4,
    "Amount of game ticks executed": 4900,
    "metrics": {
      "Player Manager - Check Player Health": 0.0010290997959183628,
      "Player Manager - Update GameTick Total": 0.013509925306122455,
      "Player Manager - Update Ship Movement": 0.002331198163265334,
      "Player Manager - Update SpaceShip": 0.004569744693877559
    },
    "Slow game ticks (x3.5 average)": 24,
    "Max Update GameTick time": 5.875875
  },
  "Director Manager": {
    "Average Update GameTick Time": 0.005838160622678177,
    "Min Update Game Tick time": 0.0,
    "Amount of game ticks executed": 5653,
    "metrics": {
      "Director Manager - Update Difficulty Coefficient": 0.0018890792961112415,
      "Director Manager - Update Director": 0.3265,
      "Director Manager - Update GameTick Total": 0.005838160622678177,
      "Director Manager - Distribute Credits": 7.756132956767273E-4
    },
    "Slow game ticks (x3.5 average)": 199,
    "Max Update GameTick time": 0.333166
  },
  "Level Manager": {
    "Average Update GameTick Time": 0.050023441358570606,
    "Min Update Game Tick time": 0.0,
    "Amount of game ticks executed": 5653,
    "metrics": {
      "Level Manager - Handle End Of Song Behaviour": 0.05817758384013899,
      "Level Manager - Update GameTick Total": 0.050023441358570606,
      "Level Manager - Finish Level": 0.055291,
      "Level Manager - Spawn Enemy": 0.239459
    },
    "Slow game ticks (x3.5 average)": 326,
    "Max Update GameTick time": 1.497541
  },
  "GameBoard": {
    "Average Update GameTick Time": 0.0,
    "Min Update Game Tick time": 1.7976931348623157E308,
    "Amount of game ticks executed": 0,
    "metrics": {
      "Draw Objects": 1.059957552175451
    },
    "Slow game ticks (x3.5 average)": 0,
    "Max Update GameTick time": 0.0
  },
  "Explosion Manager": {
    "Average Update GameTick Time": 0.002274708775510235,
    "Min Update Game Tick time": 1.25E-4,
    "Amount of game ticks executed": 4900,
    "metrics": {
      "Explosion Manager - Update Explosions": 3.417646938775503E-4,
      "Explosion Manager - Update GameTick Total": 0.002274708775510235
    },
    "Slow game ticks (x3.5 average)": 54,
    "Max Update GameTick time": 0.435416
  },
  "Thorns Damage Dealer": {
    "Average Update GameTick Time": 0.0017605658942154814,
    "Min Update Game Tick time": 1.25E-4,
    "Amount of game ticks executed": 5653,
    "metrics": {
      "Thorns Damage Dealer - Update GameTick Total": 0.0017605658942154814,
      "Thorns Damage Dealer - Activate Delayed Thorn Attacks": 1.1216787546435106E-4
    },
    "Slow game ticks (x3.5 average)": 48,
    "Max Update GameTick time": 0.110125
  },
  "Missile Manager": {
    "Average Update GameTick Time": 0.20073642469387745,
    "Min Update Game Tick time": 0.001667,
    "Amount of game ticks executed": 4900,
    "metrics": {
      "Missile Manager - Update Laserbeams": 0.011357876734693797,
      "Missile Manager - Update GameTick Total": 0.20073642469387745,
      "Missile Manager - Trigger Missile Actions": 6.711695918367349E-4,
      "Missile Manager - Remove Invisible Projects": 0.0016517624489795983,
      "Missile Manager - Check Missile Collision": 0.133837448163265,
      "Missile Manager - Move Missiles": 0.045143152653061194
    },
    "Slow game ticks (x3.5 average)": 197,
    "Max Update GameTick time": 3.907833
  },
  "Audio Manager": {
    "Average Update GameTick Time": 0.08505343693877533,
    "Min Update Game Tick time": 0.0,
    "Amount of game ticks executed": 4900,
    "metrics": {
      "Audio Manager - Reset Clips": 0.25345555073349646,
      "Audio Manager - Update GameTick Total": 0.08505343693877533
    },
    "Slow game ticks (x3.5 average)": 353,
    "Max Update GameTick time": 3.455708
  },
  "Friendly Manager": {
    "Average Update GameTick Time": 0.1218548785714287,
    "Min Update Game Tick time": 0.004875,
    "Amount of game ticks executed": 4900,
    "metrics": {
      "Friendly Manager - Activate Friendly Objects": 0.005775691836734677,
      "Friendly Manager - Check Friendly Object Collision": 0.00479804734693876,
      "Friendly Manager - Update GameTick Total": 0.1218548785714287,
      "Friendly Manager - Remove Invisible Objects": 0.0018852165306122589,
      "Friendly Manager - Spawn Finished Level Portal": 4.561006122448938E-4,
      "Friendly Manager - Move Friendly Objects": 0.10090028612244929
    },
    "Slow game ticks (x3.5 average)": 324,
    "Max Update GameTick time": 1.594917
  }
}